{
  "id": 1055907624,
  "id_str": "1055907624",
  "name": "Rep. Joe Kennedy III",
  "screen_name": "RepJoeKennedy",
  "location": "",
  "description": "Official Twitter account of Congressman Joe Kennedy III, representing Massachusetts' 4th Congressional District.",
  "url": "http://t.co/a9JpcTCQqQ",
  "entities": {
    "url": {
      "urls": [
        {
          "url": "http://t.co/a9JpcTCQqQ",
          "expanded_url": "http://kennedy.house.gov",
          "display_url": "kennedy.house.gov",
          "indices": [
            0,
            22
          ]
        }
      ]
    },
    "description": {
      "urls": [

      ]
    }
  },
  "protected": false,
  "followers_count": 16346,
  "friends_count": 594,
  "listed_count": 529,
  "created_at": "Wed Jan 02 19:33:36 +0000 2013",
  "favourites_count": 0,
  "utc_offset": -14400,
  "time_zone": "Eastern Time (US & Canada)",
  "geo_enabled": false,
  "verified": true,
  "statuses_count": 2063,
  "lang": "en",
  "status": {
    "created_at": "Fri Jul 31 19:12:54 +0000 2015",
    "id": 627195246309449728,
    "id_str": "627195246309449728",
    "text": "Honored to present @WatertownPD's Sgt MacLellan w/ Bravery Award for his actions following Boston Marathon Bombing. http://t.co/pYmGN5FeHX",
    "source": "<a href=\"http://twitter.com\" rel=\"nofollow\">Twitter Web Client</a>",
    "truncated": false,
    "in_reply_to_status_id": null,
    "in_reply_to_status_id_str": null,
    "in_reply_to_user_id": null,
    "in_reply_to_user_id_str": null,
    "in_reply_to_screen_name": null,
    "geo": null,
    "coordinates": null,
    "place": null,
    "contributors": null,
    "retweet_count": 12,
    "favorite_count": 24,
    "entities": {
      "hashtags": [

      ],
      "symbols": [

      ],
      "user_mentions": [
        {
          "screen_name": "WatertownPD",
          "name": "Watertown Police ",
          "id": 252158401,
          "id_str": "252158401",
          "indices": [
            19,
            31
          ]
        }
      ],
      "urls": [

      ],
      "media": [
        {
          "id": 627195245629865984,
          "id_str": "627195245629865984",
          "indices": [
            116,
            138
          ],
          "media_url": "http://pbs.twimg.com/media/CLQ-wLyVAAAUbun.jpg",
          "media_url_https": "https://pbs.twimg.com/media/CLQ-wLyVAAAUbun.jpg",
          "url": "http://t.co/pYmGN5FeHX",
          "display_url": "pic.twitter.com/pYmGN5FeHX",
          "expanded_url": "http://twitter.com/RepJoeKennedy/status/627195246309449728/photo/1",
          "type": "photo",
          "sizes": {
            "small": {
              "w": 340,
              "h": 255,
              "resize": "fit"
            },
            "medium": {
              "w": 600,
              "h": 450,
              "resize": "fit"
            },
            "thumb": {
              "w": 150,
              "h": 150,
              "resize": "crop"
            },
            "large": {
              "w": 1024,
              "h": 768,
              "resize": "fit"
            }
          }
        }
      ]
    },
    "favorited": false,
    "retweeted": false,
    "possibly_sensitive": false,
    "lang": "en"
  },
  "contributors_enabled": false,
  "is_translator": false,
  "is_translation_enabled": false,
  "profile_background_color": "10214A",
  "profile_background_image_url": "http://pbs.twimg.com/profile_background_images/753614680/bf4994cb7bc6e502beab95cb37f946a5.jpeg",
  "profile_background_image_url_https": "https://pbs.twimg.com/profile_background_images/753614680/bf4994cb7bc6e502beab95cb37f946a5.jpeg",
  "profile_background_tile": false,
  "profile_image_url": "http://pbs.twimg.com/profile_images/594153406287085570/LFsF3LTw_normal.jpg",
  "profile_image_url_https": "https://pbs.twimg.com/profile_images/594153406287085570/LFsF3LTw_normal.jpg",
  "profile_banner_url": "https://pbs.twimg.com/profile_banners/1055907624/1433181651",
  "profile_link_color": "BF1B1B",
  "profile_sidebar_border_color": "FFFFFF",
  "profile_sidebar_fill_color": "DDEEF6",
  "profile_text_color": "333333",
  "profile_use_background_image": true,
  "has_extended_profile": false,
  "default_profile": false,
  "default_profile_image": false,
  "following": false,
  "follow_request_sent": false,
  "notifications": false
}